{
  "data": [
    {
      "id": "437480-championship-surfer",
      "title": "Championship Surfer",
      "path": "/ps/437480-championship-surfer"
    },
    {
      "id": "576811-chaos-break",
      "title": "Chaos Break",
      "path": "/ps/576811-chaos-break"
    },
    {
      "id": "572730-chaos-control",
      "title": "Chaos Control",
      "path": "/ps/572730-chaos-control"
    },
    {
      "id": "576463-charumera",
      "title": "Charumera",
      "path": "/ps/576463-charumera"
    },
    {
      "id": "914423-covert-ops-nuclear-dawn",
      "title": "Chase the Express",
      "path": "/ps/914423-covert-ops-nuclear-dawn"
    },
    {
      "id": "575267-check-mate",
      "title": "Check Mate",
      "path": "/ps/575267-check-mate"
    },
    {
      "id": "572731-checkmate-ii",
      "title": "Checkmate",
      "path": "/ps/572731-checkmate-ii"
    },
    {
      "id": "572731-checkmate-ii",
      "title": "Checkmate II",
      "path": "/ps/572731-checkmate-ii"
    },
    {
      "id": "572732-cheesy",
      "title": "Cheesy",
      "path": "/ps/572732-cheesy"
    },
    {
      "id": "566042-chess",
      "title": "Chess",
      "path": "/ps/566042-chess"
    },
    {
      "id": "566087-chess-and-reversi",
      "title": "Chess & Reversi",
      "path": "/ps/566087-chess-and-reversi"
    },
    {
      "id": "577170-chess-2000",
      "title": "Chess 2000",
      "path": "/ps/577170-chess-2000"
    },
    {
      "id": "572416-the-chessmaster-3-d",
      "title": "Chessmaster 3-D, The",
      "path": "/ps/572416-the-chessmaster-3-d"
    },
    {
      "id": "196910-chessmaster-ii",
      "title": "Chessmaster II",
      "path": "/ps/196910-chessmaster-ii"
    },
    {
      "id": "572416-the-chessmaster-3-d",
      "title": "Chessmaster, The",
      "path": "/ps/572416-the-chessmaster-3-d"
    },
    {
      "id": "565588-who-wants-to-be-a-millionaire",
      "title": "Chi vuol essere miliardario?",
      "path": "/ps/565588-who-wants-to-be-a-millionaire"
    },
    {
      "id": "257932-who-wants-to-be-a-millionaire-2nd-edition-eu",
      "title": "Chi vuol essere milionario? - Seconda edizione",
      "path": "/ps/257932-who-wants-to-be-a-millionaire-2nd-edition-eu"
    },
    {
      "id": "572733-chibi-maruko-chan-maruko-enikki-world",
      "title": "Chibi Maruko-Chan: Maruko Enikki World",
      "path": "/ps/572733-chibi-maruko-chan-maruko-enikki-world"
    },
    {
      "id": "575322-chibi-chara-game-gingaeiyu-densetsu",
      "title": "Chibi-Chara Game Gingaeiyu Densetsu",
      "path": "/ps/575322-chibi-chara-game-gingaeiyu-densetsu"
    },
    {
      "id": "339776-chicken-run",
      "title": "Chicken Run",
      "path": "/ps/339776-chicken-run"
    },
    {
      "id": "575089-chiisana-kyojin-microman",
      "title": "Chiisana Kyojin Microman",
      "path": "/ps/575089-chiisana-kyojin-microman"
    },
    {
      "id": "577889-chiisana-oukoku-eltoria",
      "title": "Chiisana Oukoku Eltoria",
      "path": "/ps/577889-chiisana-oukoku-eltoria"
    },
    {
      "id": "563002-crossroad-crisis",
      "title": "Chiki Chiki Chicken",
      "path": "/ps/563002-crossroad-crisis"
    },
    {
      "id": "199241-wacky-races",
      "title": "Chiki Chiki Machine Mou Race",
      "path": "/ps/199241-wacky-races"
    },
    {
      "id": "573820-chill",
      "title": "Chill",
      "path": "/ps/573820-chill"
    },
    {
      "id": "924694-china-the-forbidden-city",
      "title": "China: The Forbidden City",
      "path": "/ps/924694-china-the-forbidden-city"
    },
    {
      "id": "579267-chinmoku-no-kantai",
      "title": "Chinmoku no Kantai",
      "path": "/ps/579267-chinmoku-no-kantai"
    },
    {
      "id": "575384-adventure-of-little-ralph",
      "title": "Chippoke Ralph no Daibouken: The Adventure of Little Ralph",
      "path": "/ps/575384-adventure-of-little-ralph"
    },
    {
      "id": "572742-choaniki-kyuukyoku-muteki-ginga-saikyou-otoko",
      "title": "Cho Aniki",
      "path": "/ps/572742-choaniki-kyuukyoku-muteki-ginga-saikyou-otoko"
    },
    {
      "id": "576814-cho-nazo-oh",
      "title": "Cho-Nazo-Oh",
      "path": "/ps/576814-cho-nazo-oh"
    },
    {
      "id": "572742-choaniki-kyuukyoku-muteki-ginga-saikyou-otoko",
      "title": "Choaniki: Kyuukyoku Muteki Ginga Saikyou Otoko",
      "path": "/ps/572742-choaniki-kyuukyoku-muteki-ginga-saikyou-otoko"
    },
    {
      "id": "576596-chocobo-collection",
      "title": "Chocobo Collection",
      "path": "/ps/576596-chocobo-collection"
    },
    {
      "id": "572736-chocobo-no-fushigi-na-dungeon",
      "title": "Chocobo no Fushigi na Dungeon",
      "path": "/ps/572736-chocobo-no-fushigi-na-dungeon"
    },
    {
      "id": "196912-chocobos-dungeon-2",
      "title": "Chocobo no Fushigi na Dungeon 2",
      "path": "/ps/196912-chocobos-dungeon-2"
    },
    {
      "id": "196911-chocobo-racing",
      "title": "Chocobo Racing",
      "path": "/ps/196911-chocobo-racing"
    },
    {
      "id": "196911-chocobo-racing",
      "title": "Chocobo Racing: Genkai e no Road",
      "path": "/ps/196911-chocobo-racing"
    },
    {
      "id": "576595-chocobo-stallion",
      "title": "Chocobo Stallion",
      "path": "/ps/576595-chocobo-stallion"
    },
    {
      "id": "196912-chocobos-dungeon-2",
      "title": "Chocobo's Dungeon 2",
      "path": "/ps/196912-chocobos-dungeon-2"
    },
    {
      "id": "567176-chocolate-kiss",
      "title": "Chocolate Kiss",
      "path": "/ps/567176-chocolate-kiss"
    },
    {
      "id": "572737-penny-racers",
      "title": "Choro Q",
      "path": "/ps/572737-penny-racers"
    },
    {
      "id": "196914-choro-q-2",
      "title": "Choro Q 2",
      "path": "/ps/196914-choro-q-2"
    },
    {
      "id": "572738-choro-q-3",
      "title": "Choro Q 3",
      "path": "/ps/572738-choro-q-3"
    },
    {
      "id": "572739-choro-q-jet-rainbow-wings",
      "title": "Choro Q Jet: Rainbow Wings",
      "path": "/ps/572739-choro-q-jet-rainbow-wings"
    },
    {
      "id": "573408-choro-q-marine-q-boat",
      "title": "Choro Q Marine: Q-Boat",
      "path": "/ps/573408-choro-q-marine-q-boat"
    },
    {
      "id": "572737-penny-racers",
      "title": "Choro Q Ver. 1.02",
      "path": "/ps/572737-penny-racers"
    },
    {
      "id": "562895-choro-q-wonderful",
      "title": "Choro Q Wonderful!",
      "path": "/ps/562895-choro-q-wonderful"
    },
    {
      "id": "576026-chou-hatsumei-boy-kanipan-hirameki-wonderland",
      "title": "Chou Hatsumei Boy Kanipan: Hirameki Wonderland",
      "path": "/ps/576026-chou-hatsumei-boy-kanipan-hirameki-wonderland"
    },
    {
      "id": "576535-chou-jiryoku-senshi-microman-generation-2000",
      "title": "Chou Jiryoku Senshi Microman: Generation 2000",
      "path": "/ps/576535-chou-jiryoku-senshi-microman-generation-2000"
    },
    {
      "id": "572741-chou-mashin-eiyuuden-wataru-another-step",
      "title": "Chou Mashin Eiyuuden Wataru: Another Step",
      "path": "/ps/572741-chou-mashin-eiyuuden-wataru-another-step"
    },
    {
      "id": "575051-chou-sentou-kyuugi-vanborg",
      "title": "Chou Sentou Kyuugi Vanborg",
      "path": "/ps/575051-chou-sentou-kyuugi-vanborg"
    },
    {
      "id": "575326-macross-do-you-remember-love",
      "title": "Choujikuu Yousai Macross: Do You Remember Love",
      "path": "/ps/575326-macross-do-you-remember-love"
    },
    {
      "id": "572743-choujin-gakuen-gowcaizer",
      "title": "Choujin Gakuen Gowcaizer",
      "path": "/ps/572743-choujin-gakuen-gowcaizer"
    },
    {
      "id": "572740-choukousoku-grandoll",
      "title": "Choukousoku GranDoll",
      "path": "/ps/572740-choukousoku-grandoll"
    },
    {
      "id": "578917-chris-kamaras-street-soccer",
      "title": "Chris Kamara's Street Soccer",
      "path": "/ps/578917-chris-kamaras-street-soccer"
    },
    {
      "id": "29159-chronicles-of-the-sword",
      "title": "Chronicles of the Sword",
      "path": "/ps/29159-chronicles-of-the-sword"
    },
    {
      "id": "196917-chrono-cross",
      "title": "Chrono Cross",
      "path": "/ps/196917-chrono-cross"
    },
    {
      "id": "562913-chrono-trigger",
      "title": "Chrono Trigger",
      "path": "/ps/562913-chrono-trigger"
    },
    {
      "id": "572745-chuushingura",
      "title": "Chuushingura",
      "path": "/ps/572745-chuushingura"
    },
    {
      "id": "958208-cindys-caribbean-holiday",
      "title": "Cindy's Caribbean Holiday",
      "path": "/ps/958208-cindys-caribbean-holiday"
    },
    {
      "id": "958209-cindys-fashion-world",
      "title": "Cindy's Fashion World",
      "path": "/ps/958209-cindys-fashion-world"
    },
    {
      "id": "575272-cinema-eikaiwa-a-boys-life",
      "title": "Cinema Eikaiwa: A Boy's Life",
      "path": "/ps/575272-cinema-eikaiwa-a-boys-life"
    },
    {
      "id": "575583-cinema-eikaiwa-ai-no-hate-ni",
      "title": "Cinema Eikaiwa: Ai no Hate ni",
      "path": "/ps/575583-cinema-eikaiwa-ai-no-hate-ni"
    },
    {
      "id": "575105-cinema-eikaiwa-arashi-ga-oka",
      "title": "Cinema Eikaiwa: Arashi ga Oka",
      "path": "/ps/575105-cinema-eikaiwa-arashi-ga-oka"
    },
    {
      "id": "575052-cinema-eikaiwa-interceptor",
      "title": "Cinema Eikaiwa: Interceptor",
      "path": "/ps/575052-cinema-eikaiwa-interceptor"
    },
    {
      "id": "575005-cinema-eikaiwa-tengokuni-ikenai-papa",
      "title": "Cinema Eikaiwa: Tengokuni Ikenai Papa",
      "path": "/ps/575005-cinema-eikaiwa-tengokuni-ikenai-papa"
    },
    {
      "id": "575327-cinema-eikaiwa-zombie",
      "title": "Cinema Eikaiwa: Zombie",
      "path": "/ps/575327-cinema-eikaiwa-zombie"
    },
    {
      "id": "575000-circadia",
      "title": "Circadia",
      "path": "/ps/575000-circadia"
    },
    {
      "id": "572746-circuit-beat",
      "title": "Circuit Beat",
      "path": "/ps/572746-circuit-beat"
    },
    {
      "id": "196921-circuit-breakers",
      "title": "Circuit Breakers",
      "path": "/ps/196921-circuit-breakers"
    },
    {
      "id": "572747-city-bravo",
      "title": "City Bravo!",
      "path": "/ps/572747-city-bravo"
    },
    {
      "id": "578160-city-bravo-business-hen",
      "title": "City Bravo! Business Hen",
      "path": "/ps/578160-city-bravo-business-hen"
    },
    {
      "id": "196923-the-city-of-lost-children",
      "title": "City of Lost Children, The",
      "path": "/ps/196923-the-city-of-lost-children"
    },
    {
      "id": "196927-civilization-ii",
      "title": "Civilization II",
      "path": "/ps/196927-civilization-ii"
    },
    {
      "id": "572749-civizard-majutsu-no-keifu",
      "title": "Civizard: Majutsu no Keifu",
      "path": "/ps/572749-civizard-majutsu-no-keifu"
    },
    {
      "id": "572750-classic-road",
      "title": "Classic Road",
      "path": "/ps/572750-classic-road"
    },
    {
      "id": "575246-classic-road-2",
      "title": "Classic Road 2",
      "path": "/ps/575246-classic-road-2"
    },
    {
      "id": "572751-classic-road-yuushun-2",
      "title": "Classic Road Yuushun 2",
      "path": "/ps/572751-classic-road-yuushun-2"
    },
    {
      "id": "285293-clayfighter-extreme",
      "title": "ClayFighter Extreme",
      "path": "/ps/285293-clayfighter-extreme"
    },
    {
      "id": "581465-cleopatra-fortune",
      "title": "Cleopatra Fortune",
      "path": "/ps/581465-cleopatra-fortune"
    },
    {
      "id": "581465-cleopatra-fortune",
      "title": "Cleopatra's Fortune",
      "path": "/ps/581465-cleopatra-fortune"
    },
    {
      "id": "576175-click-manga-click-no-hi",
      "title": "Click Manga: Click no Hi",
      "path": "/ps/576175-click-manga-click-no-hi"
    },
    {
      "id": "576030-click-manga-dynamic-robot-taisen-1-shutsugeki-kyoui-robot-no",
      "title": "Click Manga: Dynamic Robot Taisen 1: Shutsugeki! Kyoui Robot no Gundan!!",
      "path": "/ps/576030-click-manga-dynamic-robot-taisen-1-shutsugeki-kyoui-robot-no"
    },
    {
      "id": "576524-click-manga-dynamic-robot-taisen-2-kyoufu-akuma-zoku",
      "title": "Click Manga: Dynamic Robot Taisen 2: Kyoufu! Akuma Zoku Fukkatsu",
      "path": "/ps/576524-click-manga-dynamic-robot-taisen-2-kyoufu-akuma-zoku"
    },
    {
      "id": "576027-click-manga-ginga-eiyuu-densetsu-1",
      "title": "Click Manga: Ginga Eiyuu Densetsu 1",
      "path": "/ps/576027-click-manga-ginga-eiyuu-densetsu-1"
    },
    {
      "id": "576376-click-manga-ginga-eiyuu-densetsu-2",
      "title": "Click Manga: Ginga Eiyuu Densetsu 2",
      "path": "/ps/576376-click-manga-ginga-eiyuu-densetsu-2"
    },
    {
      "id": "580816-click-manga-ginga-eiyuu-densetsu-3",
      "title": "Click Manga: Ginga Eiyuu Densetsu 3",
      "path": "/ps/580816-click-manga-ginga-eiyuu-densetsu-3"
    },
    {
      "id": "580817-click-manga-marie-no-atelier",
      "title": "Click Manga: Marie no Atelier",
      "path": "/ps/580817-click-manga-marie-no-atelier"
    },
    {
      "id": "576028-click-manga-opera-za-no-kaijin",
      "title": "Click Manga: Opera Za no Kaijin",
      "path": "/ps/576028-click-manga-opera-za-no-kaijin"
    },
    {
      "id": "580818-click-manga-shin-dragon-half",
      "title": "Click Manga: Shin Dragon Half",
      "path": "/ps/580818-click-manga-shin-dragon-half"
    },
    {
      "id": "575020-click-medic",
      "title": "Click Medic",
      "path": "/ps/575020-click-medic"
    },
    {
      "id": "196936-clock-tower",
      "title": "Clock Tower",
      "path": "/ps/196936-clock-tower"
    },
    {
      "id": "196937-clock-tower-ii-the-struggle-within",
      "title": "Clock Tower : Ghost Head",
      "path": "/ps/196937-clock-tower-ii-the-struggle-within"
    },
    {
      "id": "196936-clock-tower",
      "title": "Clock Tower 2",
      "path": "/ps/196936-clock-tower"
    },
    {
      "id": "196937-clock-tower-ii-the-struggle-within",
      "title": "Clock Tower II: The Struggle Within",
      "path": "/ps/196937-clock-tower-ii-the-struggle-within"
    },
    {
      "id": "196937-clock-tower-ii-the-struggle-within",
      "title": "Clock Tower: Ghost Head",
      "path": "/ps/196937-clock-tower-ii-the-struggle-within"
    },
    {
      "id": "562807-clock-tower-the-first-fear",
      "title": "Clock Tower: The First Fear",
      "path": "/ps/562807-clock-tower-the-first-fear"
    },
    {
      "id": "572754-clockwerx",
      "title": "ClockWerx",
      "path": "/ps/572754-clockwerx"
    },
    {
      "id": "572755-cocktail-harmony",
      "title": "Cocktail Harmony",
      "path": "/ps/572755-cocktail-harmony"
    },
    {
      "id": "580504-cocktail-no-recipe",
      "title": "Cocktail no Recipe",
      "path": "/ps/580504-cocktail-no-recipe"
    },
    {
      "id": "205548-codemasters-demo-cd",
      "title": "Codemasters Demo CD",
      "path": "/ps/205548-codemasters-demo-cd"
    }
  ]
}